setup.py
pyrank/__init__.py
pyrank/pyrank.py
pyrank.egg-info/PKG-INFO
pyrank.egg-info/SOURCES.txt
pyrank.egg-info/dependency_links.txt
pyrank.egg-info/not-zip-safe
pyrank.egg-info/top_level.txt