Metadata-Version: 1.0
Name: pyrank
Version: 0.1
Summary: Rank the rankers
Home-page: http://github.com/mirri66/pyrank
Author: Grace Tang
Author-email: tsmgrace@gmail.com
License: MIT
Platform: UNKNOWN
